jrpymlbestprac/__init__.py
jrpymlbestprac/__version__.py
jrpymlbestprac/extra_scripts/example_projects/good_project/.gitignore
jrpymlbestprac/extra_scripts/example_projects/good_project/data/.gitignore
jrpymlbestprac/extra_scripts/example_projects/good_project/main.py
jrpymlbestprac/extra_scripts/example_projects/good_project/setup.cfg
jrpymlbestprac/extra_scripts/example_projects/good_project/utils/__init__.py
jrpymlbestprac/extra_scripts/example_projects/good_project/utils/data/__init__.py
jrpymlbestprac/extra_scripts/example_projects/good_project/utils/data/preprocessing.py
jrpymlbestprac/extra_scripts/example_projects/good_project/utils/data/storage.py
jrpymlbestprac/extra_scripts/example_projects/good_project/utils/deployment/__init__.py
jrpymlbestprac/extra_scripts/example_projects/good_project/utils/deployment/deployment.py
jrpymlbestprac/extra_scripts/example_projects/good_project/utils/modelling/__init__.py
jrpymlbestprac/extra_scripts/example_projects/good_project/utils/modelling/build.py
jrpymlbestprac/extra_scripts/example_projects/good_project/utils/modelling/ingredients.py
jrpymlbestprac/extra_scripts/example_projects/good_project/utils/modelling/predictions.py
jrpymlbestprac/extra_scripts/example_projects/good_project/utils/modelling/reporting.py
jrpymlbestprac/extra_scripts/example_projects/good_project/utils/modelling/scoring.py
jrpymlbestprac/extra_scripts/example_projects/good_project/utils/modelling/versioning.py
jrpymlbestprac-0.1.3.dist-info/METADATA
jrpymlbestprac-0.1.3.dist-info/WHEEL
jrpymlbestprac-0.1.3.dist-info/RECORD
